evoseal/__init__.py
evoseal/__version__.py
evoseal/config.py
evoseal/py.typed
evoseal/testrunner.py
evoseal/agents/__init__.py
evoseal/agents/agentic_system.py
evoseal/agents/agentic_system_example.py
evoseal/agents/agentic_workflow_agent.py
evoseal/cli/__init__.py
evoseal/cli/base.py
evoseal/cli/main.py
evoseal/cli/commands/__init__.py
evoseal/cli/commands/config.py
evoseal/cli/commands/dgm.py
evoseal/cli/commands/export.py
evoseal/cli/commands/init.py
evoseal/cli/commands/openevolve.py
evoseal/cli/commands/pipeline.py
evoseal/cli/commands/seal.py
evoseal/cli/commands/start.py
evoseal/cli/commands/status.py
evoseal/cli/commands/stop.py
evoseal/cli/utils/__init__.py
evoseal/cli/utils/logging.py
evoseal/core/__init__.py
evoseal/core/checkpoint_manager.py
evoseal/core/controller.py
evoseal/core/error_recovery.py
evoseal/core/errors.py
evoseal/core/evaluator.py
evoseal/core/events.py
evoseal/core/evolution_pipeline.py
evoseal/core/experiment_database.py
evoseal/core/experiment_integration.py
evoseal/core/improvement_validator.py
evoseal/core/logging_system.py
evoseal/core/metrics_tracker.py
evoseal/core/regression_detector.py
evoseal/core/repository.py
evoseal/core/resilience.py
evoseal/core/resilience_integration.py
evoseal/core/rollback_manager.py
evoseal/core/safety_integration.py
evoseal/core/selection.py
evoseal/core/testrunner.py
evoseal/core/version_database.py
evoseal/core/version_tracker.py
evoseal/core/workflow.py
evoseal/core/orchestration/__init__.py
evoseal/core/orchestration/checkpoint_manager.py
evoseal/core/orchestration/integration.py
evoseal/core/orchestration/orchestrator.py
evoseal/core/orchestration/recovery_manager.py
evoseal/core/orchestration/resource_monitor.py
evoseal/core/orchestration/types.py
evoseal/evolution/__init__.py
evoseal/evolution/data_collector.py
evoseal/evolution/models.py
evoseal/evolution/pattern_analyzer.py
evoseal/evolution/training_data_builder.py
evoseal/examples/__init__.py
evoseal/examples/basic/__init__.py
evoseal-0.3.4.dist-info/licenses/LICENSE
evoseal-0.3.4.dist-info/licenses/NOTICE
evoseal-0.3.4.dist-info/METADATA
evoseal-0.3.4.dist-info/WHEEL
evoseal-0.3.4.dist-info/entry_points.txt
evoseal-0.3.4.dist-info/top_level.txt
evoseal-0.3.4.dist-info/RECORD
