Metadata-Version: 2.4
Name: evoseal
Version: 0.3.4
Summary: EVOSEAL: An advanced AI system integrating DGM, OpenEvolve, and SEAL
Author: Kresna Sucandra
License: Apache-2.0
Classifier: Development Status :: 3 - Alpha
Classifier: Intended Audience :: Science/Research
Classifier: License :: OSI Approved :: Apache Software License
Classifier: Programming Language :: Python :: 3
Classifier: Programming Language :: Python :: 3.9
Classifier: Programming Language :: Python :: 3.10
Classifier: Topic :: Scientific/Engineering
Classifier: Topic :: Scientific/Engineering :: Artificial Intelligence
Requires-Python: >=3.9
License-File: LICENSE
License-File: NOTICE
Requires-Dist: python-dotenv>=1.0.0
Requires-Dist: pydantic>=2.0.0
Requires-Dist: PyYAML>=6.0.1
Requires-Dist: typer[all]>=0.12.0
Requires-Dist: rich>=13.0.0
Requires-Dist: requests>=2.31.0
Requires-Dist: GitPython>=3.1.40
Requires-Dist: structlog>=23.1.0
Requires-Dist: numpy>=1.24.0
Requires-Dist: pandas>=2.0.0
Requires-Dist: openai>=1.0.0
Requires-Dist: anthropic>=0.7.0
Requires-Dist: tqdm>=4.66.0
Requires-Dist: python-slugify>=8.0.0
Requires-Dist: click>=8.0.0
Requires-Dist: shellingham>=1.5.0
Provides-Extra: cli
Requires-Dist: typer[all]>=0.12.0; extra == "cli"
Requires-Dist: rich>=13.0.0; extra == "cli"
Requires-Dist: shellingham>=1.5.0; extra == "cli"
Provides-Extra: test
Requires-Dist: pytest>=8.0.0; extra == "test"
Requires-Dist: pytest-cov>=5.0.0; extra == "test"
Requires-Dist: pytest-mock>=3.12.0; extra == "test"
Requires-Dist: pytest-asyncio>=0.23.0; extra == "test"
Requires-Dist: pytest-xdist>=3.3.0; extra == "test"
Requires-Dist: pytest-timeout>=2.3.1; extra == "test"
Requires-Dist: pytest-benchmark>=4.1.0; extra == "test"
Requires-Dist: coverage>=7.0.0; extra == "test"
Requires-Dist: codecov<3.0.0,>=2.1.13; extra == "test"
Requires-Dist: jsonschema>=4.0.0; extra == "test"
Requires-Dist: psutil>=5.9.0; extra == "test"
Requires-Dist: torch>=2.0.0; (extra == "all" or extra == "test" and python_version >= "3.8") and extra == "test"
Requires-Dist: transformers>=4.30.0; (extra == "all" or extra == "test" and python_version >= "3.8") and extra == "test"
Provides-Extra: dev
Requires-Dist: black>=24.4.0; extra == "dev"
Requires-Dist: isort>=5.13.2; extra == "dev"
Requires-Dist: flake8>=7.0.0; extra == "dev"
Requires-Dist: mypy>=1.10.0; extra == "dev"
Requires-Dist: pylint>=3.1.0; extra == "dev"
Requires-Dist: ruff>=0.4.7; extra == "dev"
Requires-Dist: pre-commit>=3.6.0; extra == "dev"
Requires-Dist: types-PyYAML>=6.0.0; extra == "dev"
Requires-Dist: types-requests>=2.31.0; extra == "dev"
Requires-Dist: types-python-dateutil>=2.8.0; extra == "dev"
Requires-Dist: flake8-bugbear>=24.2.6; extra == "dev"
Requires-Dist: flake8-comprehensions>=3.14.0; extra == "dev"
Requires-Dist: pylint-pytest>=1.1.2; extra == "dev"
Requires-Dist: pylint-plugin-utils>=0.8.2; extra == "dev"
Requires-Dist: commitizen>=3.17.0; extra == "dev"
Dynamic: license-file
